zpy_alerts/__init__.py
zpy_alerts/alerts/__init__.py
zpy_alerts/alerts/application/__init__.py
zpy_alerts/alerts/application/alert_processor.py
zpy_alerts/alerts/domain/__init__.py
zpy_alerts/alerts/domain/constants/__init__.py
zpy_alerts/alerts/domain/constants/alert_types.py
zpy_alerts/alerts/domain/entities/__init__.py
zpy_alerts/alerts/domain/entities/alert_data.py
zpy_alerts/alerts/domain/entities/delivery_result.py
zpy_alerts/alerts/domain/entities/entities.py
zpy_alerts/alerts/domain/entities/filters.py
zpy_alerts/alerts/domain/entities/notifiers.py
zpy_alerts/alerts/infrastructure/__init__.py
zpy_alerts/alerts/infrastructure/filters/__init__.py
zpy_alerts/alerts/infrastructure/filters/allow_origin_alert_filter.py
zpy_alerts/alerts/infrastructure/filters/criticality_alert_filter.py
zpy_alerts/alerts/infrastructure/filters/deny_origin_alert_filter.py
zpy_alerts/alerts/infrastructure/filters/ttl_alert_filter.py
zpy_alerts/alerts/infrastructure/filters/type_alert_filter.py
zpy_alerts/alerts/infrastructure/notifiers/__init__.py
zpy_alerts/alerts/infrastructure/notifiers/options.py
zpy_alerts/alerts/infrastructure/notifiers/telegram/__init__.py
zpy_alerts/alerts/infrastructure/notifiers/telegram/objects.py
zpy_alerts/alerts/infrastructure/notifiers/telegram/telegram_notifier.py
zpy_alerts/alerts/infrastructure/notifiers/telegram/telegram_renders.py
zpy_alerts/alerts/infrastructure/notifiers/telegram/types.py
zpy_alert_manager-0.1.0.dist-info/LICENSE
zpy_alert_manager-0.1.0.dist-info/METADATA
zpy_alert_manager-0.1.0.dist-info/WHEEL
zpy_alert_manager-0.1.0.dist-info/top_level.txt
zpy_alert_manager-0.1.0.dist-info/RECORD
