Metadata-Version: 2.1
Name: zpy-alert-manager
Version: 0.1.0
Summary: Básic module for delivery alerts
Home-page: https://github.com/NoeCruzMW
Author: Noé Cruz | linkedin.com/in/zurckz/
Author-email: zurckz.services@gmail.com
Classifier: Programming Language :: Python :: 3
Classifier: License :: OSI Approved :: MIT License
Classifier: Operating System :: OS Independent
Requires-Python: >=3.12
License-File: LICENSE
Requires-Dist: zpy-api-core ==2.0.0
